skyborn/_dummy.cpython-310-darwin.so
skyborn/gradients.py
skyborn/__init__.py
skyborn/causality.py
skyborn/_dummy.c
skyborn/windspharm/standard.py
skyborn/windspharm/tools.py
skyborn/windspharm/_common.py
skyborn/windspharm/__init__.py
skyborn/windspharm/iris.py
skyborn/windspharm/xarray.py
skyborn/windspharm/tests/test_solution.py
skyborn/windspharm/tests/test_error_handling.py
skyborn/windspharm/tests/__init__.py
skyborn/windspharm/tests/utils.py
skyborn/windspharm/tests/reference.py
skyborn/windspharm/tests/test_tools.py
skyborn/windspharm/examples/__init__.py
skyborn/ROF/preprocess.py
skyborn/ROF/trend.py
skyborn/ROF/__init__.py
skyborn/ROF/model.py
skyborn/ROF/utils.py
skyborn/gridfill/__init__.py
skyborn/gridfill/_gridfill.pyx
skyborn/gridfill/_gridfill.cpython-310-darwin.so
skyborn/gridfill/xarray.py
skyborn/gridfill/gridfill.py
skyborn/gridfill/tests/test_fill.py
skyborn/gridfill/tests/test_fill_cube.py
skyborn/gridfill/tests/test_xarray.py
skyborn/gridfill/tests/_gridfill_ori.py
skyborn/gridfill/tests/__init__.py
skyborn/gridfill/tests/gridfill_backup.py
skyborn/gridfill/tests/data/soln_zonal.npy
skyborn/gridfill/tests/data/soln_cyclic.npy
skyborn/gridfill/tests/data/soln_cyclic_zonal.npy
skyborn/gridfill/tests/data/soln.npy
skyborn/gridfill/tests/data/grid.npy
skyborn/gridfill/__pycache__/gridfill.cpython-310.pyc
skyborn/gridfill/__pycache__/xarray.cpython-310.pyc
skyborn/gridfill/__pycache__/__init__.cpython-310.pyc
skyborn/plot/plotting.py
skyborn/plot/__init__.py
skyborn/plot/curved_quiver_plot.py
skyborn/plot/modplot.py
skyborn/interp/triple_to_grid.py
skyborn/interp/rcm2points.py
skyborn/interp/interpolation.py
skyborn/interp/regridding.py
skyborn/interp/rcm2rgrid.py
skyborn/interp/__init__.py
skyborn/interp/errors.py
skyborn/interp/missing_values.py
skyborn/interp/__pycache__/interpolation.cpython-310.pyc
skyborn/interp/__pycache__/rcm2rgrid.cpython-310.pyc
skyborn-0.3.16.dist-info/RECORD
skyborn-0.3.16.dist-info/WHEEL
skyborn-0.3.16.dist-info/top_level.txt
skyborn-0.3.16.dist-info/METADATA
skyborn-0.3.16.dist-info/licenses/LICENSE
