Metadata-Version: 2.4
Name: skyborn
Version: 0.3.16
Summary: Atmospheric science research utilities
Author-email: Qianye Su <suqianye2000@gmail.com>
License-Expression: BSD-3-Clause
Project-URL: Homepage, https://github.com/QianyeSu/Skyborn
Project-URL: Documentation, https://skyborn.readthedocs.io/
Project-URL: Repository, https://github.com/QianyeSu/Skyborn
Project-URL: Bug Tracker, https://github.com/QianyeSu/Skyborn/issues
Keywords: atmospheric-science,meteorology,climate,data-analysis,grib,netcdf
Classifier: Development Status :: 4 - Beta
Classifier: Intended Audience :: Science/Research
Classifier: Topic :: Scientific/Engineering :: Atmospheric Science
Classifier: Topic :: Scientific/Engineering :: Physics
Classifier: Programming Language :: Python :: 3
Classifier: Programming Language :: Python :: 3.9
Classifier: Programming Language :: Python :: 3.10
Classifier: Programming Language :: Python :: 3.11
Classifier: Programming Language :: Python :: 3.12
Classifier: Programming Language :: Python :: 3.13
Classifier: Operating System :: OS Independent
Requires-Python: >=3.9
License-File: LICENSE
Requires-Dist: numpy
Requires-Dist: xarray
Requires-Dist: matplotlib
Requires-Dist: seaborn
Requires-Dist: cartopy
Requires-Dist: netCDF4
Requires-Dist: metpy
Requires-Dist: tqdm
Requires-Dist: statsmodels
Requires-Dist: scipy
Requires-Dist: cfgrib
Requires-Dist: eccodes
Requires-Dist: scikit-learn
Requires-Dist: dask
Provides-Extra: dev
Requires-Dist: pytest>=7.0.0; extra == "dev"
Requires-Dist: pytest-cov>=4.0.0; extra == "dev"
Requires-Dist: black>=22.0.0; extra == "dev"
Requires-Dist: flake8>=5.0.0; extra == "dev"
Requires-Dist: mypy>=1.0.0; extra == "dev"
Requires-Dist: jupyterlab>=3.0.0; extra == "dev"
Provides-Extra: docs
Requires-Dist: sphinx>=5.0.0; extra == "docs"
Requires-Dist: sphinx-book-theme>=1.0.0; extra == "docs"
Requires-Dist: myst-nb>=0.17.0; extra == "docs"
Requires-Dist: sphinx-autodoc-typehints>=1.0.0; extra == "docs"
Requires-Dist: sphinx-copybutton>=0.5.0; extra == "docs"
Requires-Dist: jupyter-book>=0.15.0; extra == "docs"
Requires-Dist: toml>=0.10.0; extra == "docs"
Dynamic: license-file
